Workbook

Sheet Readme
A1: Document History
A2: Name of the Artifact | B2: TCS Security Design Review Checklist
A3: Version | B3: 4.0
A4: Release Date | B4: 45888
A6: Revision History
A7: Date | B7: Release No. | C7: Remarks
A8: 43466 | B8: 1.0 | C8: Formal Release of the document
A9: 45075 | B9: 2.0 | C9: Objective based questions for the security quality characteristics.
A10: 45117 | B10: 3.0 | C10: Added internet and intranet facing option under Asset Info tab and added the relevant changes in the checklist and report tab.
A11: 45888 | B11: 4.0 | C11: Added Gen AI security design guidelines
A12: © Copyright [2023], Tata Consultancy Services Limited. All Rights Reserved. Document ID CGKD009336 Unauthorized access, copying, replication, distribution, transmission, modification, adaptation or translation or use without express written permission is prohibited.
A15: Usage Guidelines
A16: • Asset details to be filled by the asset team in the Asset Info sheet. Answer the questions related to the asset in the Contextual Questions table. • Checklist sheet consists of all the line items that need to be addressed and the report sheet comprises the overall review report including the approval status. •The Applicability column in the Checklist sheet shows whether that particular line item is applicable or not; if it is 'Yes', then the asset team needs to select an appropriate Option (column F) from the drop down and if it is 'No' or if a row is grayed out it is not applicable and thus, need not be answered. •If the asset team selects the Option 'Yes' for any line item where Security Checkpoints is 'Others' or selects the Option 'No' for any line item that recommends something, they have to enter their comments mandatorily in the respective column; else the comments are optional. •If the asset team wants to reset the value in the Options column, they can simply delete the content in the options column. •Auto Approval column indicates whether that particular line item is eligible for auto approval or not. Y-indicates the line item is auto-approved and N not auto-approved. • Document Naming Convention: <TiparID of the asset>_Security_Design_Review_checklist.xlsx

Sheet Asset Info
A1: Asset TIPAR ID | B1: Tipar-ID
A2: Asset Information
A3: Asset Name & Version
A7: Contextual Questions
A8: Technology used
A9: Internet/Intranet facing
A10: Is it a multi-role application?
A11: Is the application dealing with Gen AI ? | B11: No | C11: =IF(B11="Yes","Please fill Gen AI Audit Sheet along with regular checklist","")
D45: =IF('Asset Info'!B8="Java","",IF('Asset Info'!B8="Python","",""))

Sheet Checklist
A1: Authentication and Password Management
A2: NFR | B2: Category | C2: Radio Options | D2: Security Checkpoints | E2: Applicability | F2: Option | G2: Remarks | H2: Application Team comments | I2: Reviewer Comments | J2: Auto Approval | K2: Conditional Warnings
A3: 1 | B3: Strong Password Policy | C3: 1 | D3: Does the application connects to customer SSO/LDAP/Identity & Access Management? | E3: =IF(COUNTIF(F4:F6,"Yes")>0,"No","Yes") -> Yes | F3: No | G3: =IF(F3="Yes","The application connects to customer SSO/LDAP/Identity & Access Management and hence no password policy managed within the application.","") | H3: no | J3: =IF(F3="Yes","Y","N") -> N
C4: 2 | D4: Is the application only a desktop application or a backend application and available as services without user authentication? | E4: =IF(OR(F3="Yes",COUNTIF(F5:F6,"Yes")>0),"No","Yes") -> Yes | G4: =IF(F4="Yes","The application is a backend application and do not have any password policy managed.","") | H4: no | J4: =IF(F4="Yes","Y","N") -> N
C5: 3 | D5: Has a strong password policy been implemented depending on the business requirements? | E5: =IF(OR(COUNTIF(F3:F4,"Yes")>0,F6="Yes"),"No","Yes") -> Yes | H5: Partially. The application enforces a minimum of 12 characters with uppercase, lowercase, numeric, and special characters; it also prevents inclusion of the user ID. Passwords are salted and hashed using PBKDF2-HMAC-SHA256 with 600,000 iterations. However, password history, expiry, breached-password screening, failed-login lockout, and rate limiting are not currently implemented and must be aligned with the organization’s password policy before production. | J5: =J7 -> N
C6: 4 | D6: Others | E6: =IF(COUNTIF(F3:F5,"Yes")>0,"No","Yes") -> Yes | J6: N | K6: =IF(AND(F6="Yes",ISBLANK(H6)),"Please enter your comments","")
C7: 3.1 | D7: Is the password policy configurable? | E7: =IF(F5="Yes","Yes","No") -> No | G7: =IF(OR(F7="No",F7="NA"),"Recommend to have password policy as configurable with min and max characters, 1 special character, 1 digit, atleast 1 upper case and 1 lower case letter. It should not allow to set last 5 passwords and force the user to reset the password periodically","") | H7: Partially implemented. The password policy is defined in backend code but is not configurable through application settings or environment variables. | J7: =J8 -> N | K7: =IF(AND(OR(F7="No",F7="NA"),ISBLANK(H7)),"Please enter your comments","")
C8: 3.1.1 | D8: =IF('Asset Info'!B9="Internet",CONCAT("Does the password policy consist of the following? Min length 8 to 12 characters, Max Length 50 to 64 characters, Atleast 1 upper case letter, Atleast 1 lower case letter, Atleast 1 digit, Atleast 1 special character,"," Password expiry after 30 or 60 days, Last five passwords are not allowed to be used while resetting the password."),CONCAT("Does the password policy consist of the following? Min length 8 to 12 characters, Max Length 50 to 64 characters,", "Atleast 1 upper case letter, Atleast 1 lower case letter, Atleast 1 digit, Atleast 1 special character" )) -> Does the password policy consist of the following? Min length 8 to 12 characters, Max Length 50 to 64 characters,Atleast 1 upper case letter, Atleast 1 lower case letter, Atleast 1 digit, Atleast 1 special character | E8: =IF(AND(F5="Yes",F7="Yes"),"Yes","No") -> No | G8: =IF(F8="Yes","Password Policy is configurable for min and max length and it contains atleast 1 special charcater, 1 digit, 1 upper case and 1 lower case character. It will not allow to set last 5 passwords and force the user to reset the password periodically.",IF(OR(F8="No",F8="NA"),"Recommend to have password policy as configurable with min and max characters, 1 special character, 1 digit, atleast 1 upper case and 1 lower case letter. It should not allow to set last 5 passwords and force the user to reset the password periodically","")) | H8: Partially implemented. Passwords require a minimum of 12 characters, uppercase, lowercase, digit, and special character. Passwords cannot contain the user ID. The configured maximum length is 128 characters, not 50–64. | J8: =IF(F8="Yes","Y","N") -> N | K8: =IF(AND(OR(F8="No",F8="NA"),ISBLANK(H8)),"Please enter your comments","")
A9: 2 | B9: Secure storage of credentials | C9: 1 | D9: =IF(OR(F3="Yes",F4="Yes"),"NA","Does the application store user credentials in DB by salting and hashing it?") -> Does the application store user credentials in DB by salting and hashing it? | E9: =IF(D9<>"NA","Yes","No") -> Yes | G9: =IF(OR(F9="No",F9="NA"),"Recommend to have store application user credenatials in DB by salting and hashing it using slow hashing algorithms like scrypt/bcrypt/PBKDF2WithHMACSHA256.PBKDF2WithHMACSHA512/Argon2id.","") | H9: Yes. The application stores passwords in the database only as salted hashes. It uses a unique cryptographically generated 16-byte salt for each password and PBKDF2-HMAC-SHA256 with 600,000 iterations. Plaintext passwords and reusable password credentials are not stored in the database. | J9: =IF(E9="No","Y",IF(OR(F9="No",F9="NA"),"N",J10)) -> N | K9: =IF(AND(OR(F9="No",F9="NA"),ISBLANK(H9)),"Please enter your comments","")
C10: 1.1 | D10: Does the application uses slow hashing algorithms like scrypt/bcrypt/PBKDF2WithHMACSHA256/PBKDF2WithHMACSHA512/Argon2id? | E10: =IF(F9="Yes","Yes","No") -> No | G10: =IF(F10="Yes","Application stores the user passwords in DB by salting and hashing it using slow hashing algorithms.",IF(OR(F10="No",F10="NA"),"Application stores the user passwords in DB by salting and hashing it. Recommend to use slow hashing algorithms like scrypt/bcrypt/PBKDF2WithHMACSHA256.PBKDF2WithHMACSHA512/Argon2id.","")) | H10: Implemented. User passwords are hashed using PBKDF2-HMAC-SHA256 with 600,000 iterations and a unique cryptographically random 16-byte salt. Password verification uses constant-time comparison. | J10: =IF(F10="Yes","Y","N") -> N | K10: =IF(AND(OR(F10="No",F10="NA"),ISBLANK(H10)),"Please enter your comments","")
A11: 3 | B11: Unique Id for each user | C11: 1 | D11: Does each user have a unique ID? | E11: =IF(D12="NA","No",IF(F12="Yes","No","Yes")) -> Yes | G11: =IF(OR(F11="No","NA"),"Recommended to have uniques ID for each user.","") -> #VALUE! | H11: Yes. Each user has a system-generated UUID as the internal primary identifier. The user ID used for login is also protected by a database uniqueness constraint, preventing duplicate accounts with the same ID. | J11: =IF(D12="NA","Y",IF(F11="Yes","Y","N")) -> N | K11: =IF(AND(OR(F11="No",F11="NA"),ISBLANK(H11)),"Please enter your comments","")
C12: 2 | D12: =IF(F4="Yes","NA","Others") -> Others | E12: =IF(D12="NA","No",IF(F11="Yes","No","Yes")) -> Yes | K12: =IF(AND(F12="Yes",ISBLANK(H12)),"Please enter your comments","")
A13: 4 | B13: Unique token for new session | C13: 1 | D13: On every successful Authentication event of the user or service, is a new session token generated and any old session associated with the same user or service invalidated? | E13: =IF(D14="NA","No",IF(F14="Yes","No","Yes")) -> Yes | G13: =IF(F13="Yes","On every successful Authentication event of the user or service, a fresh new session token generated and any old session associated with the same user or service invalidated.",IF(OR(F13="No",F13="NA"),"Recommend to generate a fresh new session token on every successful authetication and invalidate any old session associated with the same user or service.","")) | H13: Partially. A new cryptographically secure session token is generated after every successful login. However, earlier sessions for the same user are not automatically invalidated at login, so multiple concurrent sessions are currently permitted. | J13: =IF(D14="NA","Y",IF(F13="Yes","Y","N")) -> N | K13: =IF(AND(OR(F13="No",F13="NA"),ISBLANK(H13)),"Please enter your comments","")
C14: 2 | D14: =IF(F4="Yes","NA","Others") -> Others | E14: =IF(D14="NA","No",IF(F13="Yes","No","Yes")) -> Yes | K14: =IF(AND(F14="Yes",ISBLANK(H14)),"Please enter your comments","")
A15: 5 | B15: Logout | C15: 1 | D15: Does the application inform the user on logging out and seek confirmation to logout the user on clicking Logout button? | E15: =IF(D16="NA","No",IF(F16="Yes","No","Yes")) -> Yes | G15: =IF(OR(F15="No","NA"),"Recommend to inform the user on logging out when logout button is clicked.","") -> #VALUE! | H15: no | J15: =IF(D16="NA","Y",IF(F15<>"Yes","N",J17)) -> N | K15: =IF(AND(OR(F15="No",F15="NA"),ISBLANK(H15)),"Please enter your comments","")
C16: 2 | D16: =IF(F4="Yes","NA","Others") -> Others | E16: =IF(D16="NA","No",IF($F15<>"Yes","Yes","No")) -> Yes | H16: Logout invalidates the active server-side session, deletes the browser’s session cookie, clears the authenticated user state, and prevents further use of that token. A confirmation dialog may be added if required by the organization’s user-experience or security policy. | K16: =IF(AND(F16="Yes",ISBLANK(H16)),"Please enter your comments","")
C17: 1.1 | D17: Is the session token invalidated on logout? | E17: =IF($F15="Yes","Yes","No") -> No | G17: =IF(F17="Yes","Application informs the user on logging out when logout button is clicked. Session is invalidated on logout.",IF(OR(F17="No",F17="NA"),"Application informs the user on logging out when logout button is clicked. Recommend to invalidate the session token on logout.","")) | H17: Implemented. On logout, the server-side session record is deleted from the database and the session cookie is removed, preventing reuse of the token. | J17: =IF(F17="Yes","Y","N") -> N | K17: =IF(AND(OR(F17="No",F17="NA"),ISBLANK(H17)),"Please enter your comments","")
A18: 6 | B18: Password management event logging | C18: 1 | D18: Does every password change/reset event generate an audit trail that contains parameters such as Date & Time, User ID & Success or Failure status? | E18: =IF(D19="NA","No",IF(F19="Yes","No","Yes")) -> Yes | G18: =IF(F18="Yes","Every Password Change/Reset event generate an audit trail which contains parameters like User's IP Address, Date & Time, User ID & Success or Failure status.",IF(OR(F18="No",F18="NA"),"Recommend to generate an audit trail on every password change/reset event containing parameters like User's IP Address, Date & Time, User ID & Success or Failure status.","")) | H18: no | J18: =IF(D19="NA","Y",IF(F18="Yes","Y","N")) -> N | K18: =IF(AND(OR(F18="No",F18="NA"),ISBLANK(H18)),"Please enter your comments","")
C19: 2 | D19: =IF(F4="Yes","NA","Others") -> Others | E19: =IF(D19="NA","No",IF(F18="Yes","No","Yes")) -> Yes | K19: =IF(AND(F19="Yes",ISBLANK(H19)),"Please enter your comments","")
A20: 7 | B20: Encrypted communication for secrets in transit | C20: 1 | D20: Is the authentication token or secret protected by using encryption and secure communication channels like HTTPS? | E20: =IF(D21="NA","No",IF(F21="Yes","No","Yes")) -> Yes | G20: =IF(F20="Yes","Authentication token or secret protected by using encryption and secure communication channels like HTTPS.",IF(OR(F20="No",F20="NA"),"Recommend to protect authentication token or secret by using encryption and secure communication channels like HTTPS.","")) | H20: Partially. Session tokens use secure cookies in production, but HTTPS/TLS must be enforced by the production infrastructure. | J20: =IF(D21="NA","Y",IF(F20="Yes","Y","N")) -> N | K20: =IF(AND(OR(F20="No",F20="NA"),ISBLANK(H20)),"Please enter your comments","")
C21: 2 | D21: =IF(F4="Yes","NA","Others") -> Others | E21: =IF(D21="NA","No",IF(F20="Yes","No","Yes")) -> Yes | K21: =IF(AND(F21="Yes",ISBLANK(H21)),"Please enter your comments","")
A22: 8 | B22: Secure password recovery | C22: 1 | D22: Is the user prompted to enter Security/Secret question and answer? | E22: =IF(D25="NA","No",IF(OR(F23="Yes",F25="Yes",F24="Yes"),"No","Yes")) -> Yes | H22: no | J22: =IF(D25="NA","Y",IF(AND('Asset Info'!B9="Intranet",F22="Yes"),"Y",J26)) -> N
C23: 2 | D23: Is the password reset link shared with users through mail to set their own password? | E23: =IF(D25="NA","No",IF(OR(F25="Yes",F22="Yes",F24="Yes"),"No","Yes")) -> Yes | G23: =IF(F23="Yes","Forgot password option is available. An email is send to the user with a password reset link to set the password.","") | H23: no | J23: =IF(F23="Yes","Y","N") -> N
C24: 3 | D24: Does admin reset the password? | E24: =IF(D25="NA","No",IF(OR(F22="Yes",F23="Yes",F25="Yes"),"No","Yes")) -> Yes | H24: no
C25: 4 | D25: =IF(F4="Yes","NA","Others") -> Others | E25: =IF(D25="NA","No",IF(COUNTIF(F22:F24,"Yes")>0,"No","Yes")) -> Yes | K25: =IF(AND(F25="Yes",ISBLANK(H25)),"Please enter your comments","")
C26: 1.1 | D26: Is OTP validation implemented? | E26: =IF(AND('Asset Info'!B9="Internet",F22="Yes"),"Yes","No") -> No | G26: =IF(F26="Yes","Secure Password Recovery mechanism is implemented by using multi-factor authentication elements ( for example ask security question something they know, and then send a generated token to a device/email - something they own).",IF(OR(F26="No",F26="NA"),"Recommend to have second factor of authentication like OTP for securely recovering the password.","")) | H26: no | J26: =IF(F26="Yes","Y","N") -> N | K26: =IF(AND(OR(F26="No",F26="NA"),ISBLANK(H26)),"Please enter your comments","")
C27: 3.1 | D27: Is the admin shared password forced to change on first login? | E27: =IF(F24="Yes","Yes","No") -> No | G27: =IF(ISBLANK(F27),"",IF(F27="Yes","Admin resets the password and it is forced to change on first login by the user","Recommended to force the users to change their password upon their next login after a password reset by admin")) | H27: no | J27: =IF(F27="Yes","Y","N") -> N
A28: 9 | B28: Latest version of TLS used for communication | C28: 1 | D28: Is TLSv1.2 or above used for secure communication? | E28: =IF(F29="Yes","No","Yes") -> Yes | G28: =IF(F28="Yes","TLSv1.2 or above is used for secure communication.",IF(OR(F28="No",F28="NA"),"TLSv1.2 or above is recommended to use for secure communication","")) | J28: =IF(F28="Yes","Y","N") -> N | K28: =IF(AND(OR(F28="No",F28="NA"),ISBLANK(H28)),"Please enter your comments","")
C29: 2 | D29: Others | E29: =IF(F28="Yes","No","Yes") -> Yes | K29: =IF(AND(F29="Yes",ISBLANK(H29)),"Please enter your comments","")
A30: 10 | B30: Anti-automation controls | C30: 1 | D30: =IF(F4="Yes","NA",IF('Asset Info'!B9="Internet","Is CAPTCHA enforced on publicly available pages like Login page or any page that does not require authentication?","As it is a Intranet application anti-automation controls like CAPTCHA is not mandatory.")) -> As it is a Intranet application anti-automation controls like CAPTCHA is not mandatory. | E30: =IF('Asset Info'!B9="Internet","Yes","No") -> No | G30: =IF(F30="No","Recommend to enforce CAPTCHA on publicly available pages like Login page or any page that does not require authentication","") | H30: no | J30: =IF(OR(D30="NA",'Asset Info'!B9="Intranet"),"Y",IF(F30<>"Yes","N",IF(COUNTIF(J31:J32,"Y")>0,"Y","N"))) -> N
C31: 1.1 | D31: Are third-party or standard CAPTCHA libraries used? | E31: =IF(AND(F30="Yes",F32<>"Yes"),"Yes","No") -> No | G31: =IF(F31="Yes","Application uses CAPTCHA as anti-automation control. Standard CAPTCHA libraries used for generation.","") | H31: no | J31: =IF(F31="Yes","Y","N") -> N
C32: 1.2 | D32: Is custom code used for CAPTCHA? | E32: =IF(AND(F30="Yes",F31<>"Yes"),"Yes","No") -> No | H32: no | J32: =J33 -> N
C33: 1.2.1 | D33: Is CAPTCHA generation logic available on the server side? | E33: =IF(F32="Yes","Yes","No") -> No | G33: =IF(F33="Yes","Application uses CAPTCHA as anti-automation control. Custom CAPTCHA generation done on the server side.",IF(OR(F33="No",F33="NA"),"Application uses CAPTCHA as anti-automation control. Custom CAPTCHA generation used. Recommended to generate and validate CAPTCHA on the server side.","")) | H33: no | J33: =IF(F33="Yes","Y","N") -> N
A34: 11 | B34: Multifactor authentication for sensitive transactions | C34: 1 | D34: Does the application involve sensitive transactions (like changing the shipping address for a purchase, or delegation of duties etc)? | E34: =IF(D35="NA","No",IF(F35="Yes","No","Yes")) -> Yes | G34: =IF(OR(F34="No",F34="NA"),"Application does not have any sensitive transaction","") | H34: no | J34: =IF(D35="NA","Y",IF(F34="Yes",J36,IF(NOT(ISBLANK(F34)),"Y","N"))) -> N
C35: 2 | D35: =IF(F4="Yes","NA","Others") -> Others | E35: =IF(D35="NA","No",IF(ISBLANK($F34),"Yes","No")) -> Yes | K35: =IF(AND(F35="Yes",ISBLANK(H35)),"Please enter your comments","")
C36: 1.1 | D36: Is the user re-authenticated or verified through Profile Passwords or OTP mechanism? | E36: =IF($F34="Yes","Yes","No") -> No | G36: =IF(F36="Yes","For sensitive transactions, application re-authenticates the user or verify through Profile Passwords or OTP mechanism.",IF(OR(F36="No",F36="NA"),"For sensitive transactions, recommend to re-authenticates the user or verify through Profile Passwords or OTP mechanism.","")) | H36: no | J36: =IF(F36="Yes","Y","N") -> N | K36: =IF(AND(OR(F36="No",F36="NA"),ISBLANK(H36)),"Please enter your comments","")
A37: 12 | B37: IP based restriction for critical functionality | C37: 1 | D37: Does the application have critical functionalities like admin setting certain role entitlements or payment configuration etc? | E37: =IF('Asset Info'!B10="No","No",IF(F4="Yes","No",IF(D37<>"NA","Yes","No"))) -> Yes | G37: =IF(OR(F37="No",F37="NA"),"Application do not have any critical functionality","") | H37: no | J37: =IF(E37="No","Y",IF(F4="Yes","Y",IF(F37="Yes",J38,IF(NOT(ISBLANK(F37)),"Y","N")))) -> N
C38: 1.1 | D38: Is IP based restriction enabled for accessing such functionality? | E38: =IF(F37="Yes","Yes","No") -> No | G38: =IF(F38="Yes","Application has critical functionality and Ipbased restrcition enabled for accessing such pages/functionality.",IF(OR(F38="No",F38="NA"),"Application has critical functionality. Recommend to have IP based access to those pages or functionality.","")) | H38: no | J38: =IF(F38="Yes","Y","N") -> N | K38: =IF(AND(OR(F38="No",F38="NA"),ISBLANK(H38)),"Please enter your comments","")
A39: Audit trails and logging
A40: 1 | B40: Clock synchronization for all devices and servers. | C40: 1 | D40: Does the application have the time synchronised with NTP, other applications and systems? | E40: Yes | G40: =IF(F40="Yes","The application has the time synchronised with NTP, other applications and systems.",IF(OR(F40="No",F40="NA"),"Recommended to have the time synchronised with NTP, other applications and systems.","")) | H40: no | J40: =IF(F40="Yes","Y","N") -> N | K40: =IF(AND(OR(F40="No",F40="NA"),ISBLANK(H40)),"Please enter your comments","")
A41: 2 | B41: Capture at least source IP address, timestamp, action owner Id, event Id and resource Id. | C41: 1 | D41: Are the source IP address, timestamp, action owner ID, event ID, and resource ID captured in the logs? | E41: Yes | G41: =IF(F41="Yes","Source IP address, timestamp, action owner Id, event Id and resource Id are captured in the logs.",IF(OR(F41="No",F41="NA"),"Recommended to capture source IP address, timestamp, action owner Id, event Id and resource Id.","")) | H41: Partially. Audit records capture timestamp, event ID, user ID, action, and deal/resource ID, but not source IP address. | J41: =IF(F41="Yes","Y","N") -> N | K41: =IF(AND(OR(F41="No",F41="NA"),ISBLANK(H41)),"Please enter your comments","")
A42: 3 | B42: Differentiate events from errors. | C42: 1 | D42: Does the application differentiate events from errors? | E42: Yes | G42: =IF(F42="Yes","Events and errors are differentiated.",IF(OR(F42="No",F42="NA"),"Recommended to differentiate events from errors.","")) | H42: Yes. Standard log levels such as INFO, WARNING, and ERROR differentiate operational events from errors. | J42: =IF(F42="Yes","Y","N") -> N | K42: =IF(AND(OR(F42="No",F42="NA"),ISBLANK(H42)),"Please enter your comments","")
A43: 4 | B43: Append only mode for trails and logs. | C43: 1 | D43: Are audit trails and logs configured with append only mode? | E43: Yes | G43: =IF(F43="Yes","Audit trails and logs are configured with append only mode.",IF(OR(F43="No",F43="NA"),"Recommended to have audit trails and logs as Write Once, Read Only format.","")) | H43: no | J43: =IF(F43="Yes","Y","N") -> N | K43: =IF(AND(OR(F43="No",F43="NA"),ISBLANK(H43)),"Please enter your comments","")
A44: 6 | B44: Use the standard APIs or libraries for logging. | C44: 1 | D44: =IF('Asset Info'!B8="Java","Does the application use the standard APIs or libraries for logging such as Log4j, Log4Net ?",IF('Asset Info'!B8="Python","Does the application use standard APIs or libraries for logging such as 'Logging', 'Loguru', 'Pytholog' etc?","Does the application use any standard libraries for logging? If yes, please mention in the asset team comments column.")) -> Does the application use any standard libraries for logging? If yes, please mention in the asset team comments column. | E44: Yes | G44: =IF(AND('Asset Info'!B8="Java",F44="Yes"),"Standard logging frameworks or APIs are used for logging like Log4j, Log4Net.",IF(AND('Asset Info'!B8="Python",F44="Yes"),"Standard logging frameworks or APIs are used for logging like 'Logging', 'Loguru', 'Pytholog'.","")) | H44: Yes. The backend uses Python’s standard logging library and OpenTelemetry-based tracing. | J44: =IF(AND(NOT(ISBLANK(G44)),F44="Yes"),"Y","N") -> N | K44: =IF(AND($F44="Yes",AND(ISBLANK('Asset Info'!B8),ISBLANK($H44))),"Please enter your comments","")
C45: 2 | D45: Others | K45: =IF(AND(F45="Yes",ISBLANK(H45)),"Please enter your comments","")
A46: 7 | B46: Maintain audit-trail for administrative actions separately | C46: 1 | D46: Is a seperate audit trail maintained for administrative actions? | E46: =IF('Asset Info'!B10="No","No","Yes") -> Yes | G46: =IF(F46="Yes","Seperate audit trail is maintained for administrative actions.",IF(OR(F46="No",F46="NA"),"Recomended to Maintain audit-trail for administrative actions separately.","")) | H46: no | J46: =IF('Asset Info'!B10="No","Y",IF(F46="Yes","Y","N")) -> N | K46: =IF(AND(OR(F46="No",F46="NA"),ISBLANK(H46)),"Please enter your comments","")
A47: 8 | B47: Log sensitive information in encrypted format. | C47: 1 | D47: Is sensitive information logged? | E47: =IF(D47<>"NA","Yes","No") -> Yes | G47: =IF(OR(F47="No",F47="NA"),"No sensitive information is logged.","") | H47: no | J47: =IF(F47="Yes",J48,IF(NOT(ISBLANK(F47)),"Y","N")) -> N
C48: 1.1 | D48: Is the sensitive information logged in an encrypted format? | E48: =IF(F47="Yes","Yes","No") -> No | G48: =IF(F48="Yes","Sensitive information is logged in encrypted format.",IF(OR(F48="No",F48="NA"),"Recommended to encrypt and log the sensitive information.","")) | H48: no | J48: =IF(F48="Yes","Y","N") -> N | K48: =IF(AND(OR(F48="No",F48="NA"),ISBLANK(H48)),"Please enter your comments","")
A49: 9 | B49: Plan sufficient disk space for logs. | C49: 1 | D49: Is the disk space managed (through periodic backup of log) so that adequate space is available for logging? | E49: Yes | G49: =IF(F49="Yes","Sufficient disk space for logs is planned by having periodic backups.",IF(OR(F49="No",F49="NA"),"Recommended to ensure that log files are stored in a safe location of the file system and that adequate disk space is available for logging.","")) | H49: no | J49: =IF(F49="Yes","Y","N") -> N | K49: =IF(AND(OR(F49="No",F49="NA"),ISBLANK(H49)),"Please enter your comments","")
A50: 10 | B50: Appropriately select logging strategy based on date, user or events. | C50: 1 | D50: Is date-wise logging strategy followed? | E50: =IF(COUNTIF(F51:F53,"Yes")>0,"No","Yes") -> Yes | G50: =IF(F50="Yes","Appropriate logging strategy is selected i.e., date-wise logging followed.","") | H50: Partially. Logs contain timestamps | J50: =IF(F50="Yes","Y","N") -> N | K50: =IF(AND(OR(F50="No",F50="NA"),ISBLANK(H50)),"Please enter your comments","")
C51: 2 | D51: Is user-wise logging strategy followed? | E51: =IF(OR(F50="Yes",COUNTIF(F52:F53,"Yes")>0),"No","Yes") -> Yes | G51: =IF(F51="Yes","Appropriate logging strategy is selected i.e., user-wise logging followed.","") | H51: Partially. Deal audit records capture the action owner | J51: =IF(F51="Yes","Y","N") -> N | K51: =IF(AND(OR(F51="No",F51="NA"),ISBLANK(H51)),"Please enter your comments","")
C52: 3 | D52: Is event-wise logging strategy followed? | E52: =IF(OR(COUNTIF(F50:F51,"Yes")>0,F53="Yes"),"No","Yes") -> Yes | G52: =IF(F52="Yes","Appropriate logging strategy is selected i.e., event-wise logging followed.","") | H52: Yes, partially. Audit records contain an action type, and system logs use severity levels. | J52: =IF(F52="Yes","Y","N") -> N | K52: =IF(AND(OR(F52="No",F52="NA"),ISBLANK(H52)),"Please enter your comments","")
C53: 4 | D53: Others | E53: =IF(COUNTIF(F50:F52,"Yes")>0,"No","Yes") -> Yes | K53: =IF(AND(F53="Yes",ISBLANK(H53)),"Please enter your comments","")
A54: 11 | B54: Periodically analyze logs for anomaly or misbehavior | C54: 1 | D54: Are logs analyzed periodically for anomalies or misbehaviours? | E54: =IF(D54<>"NA","Yes","No") -> Yes | G54: =IF(OR(F54="No",F54="NA"),"Recommended to analyze logs periodically for anomalies or misbehaviours.","") | H54: no | J54: =IF(F54="Yes",J55,IF(NOT(ISBLANK(F54)),"Y","N")) -> N | K54: =IF(AND(OR(F54="No",F54="NA"),ISBLANK(H54)),"Please enter your comments","")
C55: 1.1 | D55: Is it done through an automated program? | E55: =IF(F54="Yes","Yes","No") -> No | G55: =IF(F55="Yes","Logs are analyzed periodically for anomalies or misbehaviours automatically.",IF(OR(F55="No",F55="NA"),"Logs are analyzed periodically for anomalies or misbehaviours. However recommended to use an automated program to achieve it.","")) | H55: Partially implemented. The observability dashboard automatically collects and displays LLM usage, latency, failures, moderation, and token metrics. | J55: =IF(F55="Yes","Y","N") -> N | K55: =IF(AND(OR(F55="No",F55="NA"),ISBLANK(H55)),"Please enter your comments","")
A56: 12 | B56: Have restricted access for logs. | C56: 1 | D56: Is access to logs restricted to support team or admin team? | E56: Yes | G56: =IF(F56="Yes","Access is restricted to logs, support or admin team has the access.",IF(OR(F56="No",F56="NA"),"Recommended to restrict access to logs. Enable access to only support or admin team.","")) | H56: Partially. Server-log access depends on infrastructure permissions; the application does not enforce support/admin-only access. The observability page is available to authenticated users. | J56: =IF(F56="Yes","Y","N") -> N | K56: =IF(AND(OR(F56="No",F56="NA"),ISBLANK(H56)),"Please enter your comments","")
A57: 13 | B57: Encrypt admin audit-trail and protect it from admin. | C57: 1 | D57: Is the admin audit-trail encrypted and protected from the admin? | E57: =IF('Asset Info'!B10="No","No","Yes") -> Yes | G57: =IF(F57="Yes","Admin audit-trail is encrypted and protect it from admin.",IF(OR(F57="No",F57="NA"),"Recommended to encrypt admin audit-trail and protect it from admin.","")) | H57: no | J57: =IF('Asset Info'!B10="No","Y",IF(F57="Yes","Y","N")) -> N | K57: =IF(AND(OR(F57="No",F57="NA"),ISBLANK(H57)),"Please enter your comments","")
A58: Access control
A59: 1 | B59: Validate each request for authorization | C59: 1 | D59: Is every request checked for authorization before accessing a page? | E59: =IF(F4="Yes","No","Yes") -> Yes | G59: =IF(F59="Yes","Each request is validated for authorization before accesing a page.",IF(OR(F59="No",F59="NA"),"Recommended to validate each request for authorization.","")) | H59: Yes, for protected APIs. Authentication and role/deal-level authorization are checked before protected resources are accessed. Login, registration, password reset, and health-check endpoints are public. | J59: =IF(F4="Yes","Y",IF(F59="Yes","Y","N")) -> N | K59: =IF(AND(OR(F59="No",F59="NA"),ISBLANK(H59)),"Please enter your comments","")
A60: 2 | B60: Always rely on Server Side data for access control decisions | C60: 1 | D60: Are access control decisions always based on server side data? | E60: =IF(F4="Yes","No","Yes") -> Yes | G60: =IF(F60="Yes","The access control decisions are always based on server side data.",IF(OR(F60="No",F60="NA"),"Recommended that decisions for access controls are always taken based on the server side data.","")) | H60: Yes. Access-control decisions are enforced by the backend using the authenticated session, user role, and deal ownership. | J60: =IF(F4="Yes","Y",IF(F60="Yes","Y","N")) -> N | K60: =IF(AND(OR(F60="No",F60="NA"),ISBLANK(H60)),"Please enter your comments","")
A61: 3 | B61: Offer minimal functionality to anonymous users | C61: 1 | D61: Does the application have any anonymous users? | E61: =IF(F4="Yes","No",IF(D61<>"NA","Yes","No")) -> Yes | G61: =IF(OR(F61="No",F61="NA"),"There are no anonymous users.","") | H61: no | J61: =IF(F4="Yes","Y",IF(F61="Yes",J62,IF(NOT(ISBLANK(F61)),"Y","N"))) -> N | K61: =IF(AND(F61="Yes",ISBLANK(H61)),"Please enter your comments","")
C62: 1.1 | D62: Does the application offer minimal functionality to the anonymous users? | E62: =IF(F61="Yes","Yes","No") -> No | G62: =IF(F62="Yes","The application offers minimal functionality to the anonymus users.",IF(OR(F62="No",F62="NA"),"Recommended to offer minimal functionality to the anonymus users.","")) | H62: Implemented. Anonymous access is limited to authentication functions and the health endpoint. All deal, document, LLM-generation, review, and export functions require an authenticated session. | J62: =IF(F62="Yes","Y","N") -> N | K62: =IF(AND(OR(F62="No",F62="NA"),ISBLANK(H62)),"Please enter your comments","")
A63: 4 | B63: Create centralized access control system through ACL | C63: 1 | D63: Does the application have centralized access control system through ACL? | E63: =IF(D64="NA","No",IF(F64="Yes","No","Yes")) -> Yes | G63: =IF(F63="Yes","Centralized access control system is created through ACL.",IF(OR(F63="No",F63="NA"),"Recommended to create centralized access control system through ACL.","")) | H63: Partially. Server-side access control is centralized using role-based authorization and deal ownership. | J63: =IF(D64="NA","Y",IF(F63="Yes","Y","N")) -> N | K63: =IF(AND(OR(F63="No",F63="NA"),ISBLANK(H63)),"Please enter your comments","")
C64: 2 | D64: =IF(F4="Yes","NA","Others") -> Others | E64: =IF(D64="NA","No",IF(F63="Yes","No","Yes")) -> Yes | K64: =IF(AND(F64="Yes",ISBLANK(H64)),"Please enter your comments","")
A65: 5 | B65: Provide no privileges to an account when it is first created | C65: 1 | D65: Are privileges provided incrementally after creating the user intitially with zero privileges? | E65: =IF(F4="Yes","No","Yes") -> Yes | G65: =IF(F65="Yes","Privileges are provided incrimentally after creating the user intitially with zero privileges.",IF(OR(F65="No",F65="NA"),"Recommended to provide privileges incrimentally after creating the user intitially with zero privileges.","")) | H65: no | J65: =IF(F4="Yes","Y",IF(F65="Yes","Y","N")) -> N | K65: =IF(AND(OR(F65="No",F65="NA"),ISBLANK(H65)),"Please enter your comments","")
A66: 6 | B66: Classify data to perform Encryption, Hashing, Encoding or Masking | C66: 1 | D66: Does the application classify the data and perform Encryption/Hashing/Encoding or Masking on respective requirements for the data at rest and in transit? | E66: Yes | G66: =IF(F66="Yes","Data is classified to perform Encryption, Hashing, Encoding or Masking.",IF(OR(F66="No",F66="NA"),"Recommended to classify data to perform Encryption, Hashing, Encoding or Masking.","")) | H66: Partially. Passwords are salted and hashed | J66: =IF(F66="Yes","Y","N") -> N | K66: =IF(AND(OR(F66="No",F66="NA"),ISBLANK(H66)),"Please enter your comments","")
A67: 7 | B67: Restrict a normal user's access to system resources | C67: 1 | D67: Are the system resources restricted from normal users and is based on the need? | E67: Yes | G67: =IF(F67="Yes","Normal user is restricted to access the system resources and is given access based on the need.",IF(OR(F67="No",F67="NA"),"Recommended to restrict a normal user's access to system resources.","")) | H67: Partially. Server-side roles and deal ownership restrict core resources, | J67: =IF(F67="Yes","Y","N") -> N | K67: =IF(AND(OR(F67="No",F67="NA"),ISBLANK(H67)),"Please enter your comments","")
A68: 8 | B68: Maintain Audit Trails for sensitive Transactions | C68: 1 | D68: Are audit trails maintained for sensitive transactions? | E68: =IF(F34="Yes","Yes","No") -> No | G68: =IF(F68="Yes","Audit trails are maintained for sensitive transactions.",IF(OR(F68="No",F68="NA"),"Recommended to maintain Audit Trails for sensitive Transactions.","")) | H68: Database audit entries record deal creation/updates, narrative generation and version actions, submissions, approvals/denials, and exports. | J68: =IF(E68="No","Y",IF(OR(OR(F34="No",F34="NA"),F68="Yes"),"Y","N")) -> Y | K68: =IF(AND(OR(F68="No",F68="NA"),ISBLANK(H68)),"Please enter your comments","")
A69: 9 | B69: Generate sensitive content on the fly | C69: 1 | D69: Does the application generate any sensitive content like OTP or payment transaction ID etc? | E69: =IF(D69<>"NA","Yes","No") -> Yes | G69: =IF(OR(F69="No",F69="NA"),"No sensitive content is generated.","") | H69: no | J69: =IF(F69="Yes",J70,IF(NOT(ISBLANK(F69)),"Y","N")) -> N
C70: 1.1 | D70: Are the sensitive content generated on the fly and transmitted directly to the browser rather than saving it in the web server's file system? | E70: =IF(F69="Yes","Yes","No") -> No | G70: =IF(F70="Yes","Sensitive contenet is generated on the fly.",IF(OR(F70="No",F70="NA"),"Recommended to generate sensitive content on the fly and transmit it directly to the browser rather than saving it in the web server's file system.","")) | H70: PDF, DOCX, and PPTX reports are generated in memory and streamed directly to the browser without saving export files locally. Generated narratives are retained in the database, and uploaded source documents are stored on the application filesystem. | J70: =IF(F70="Yes","Y","N") -> N | K70: =IF(AND(OR(F70="No",F70="NA"),ISBLANK(H70)),"Please enter your comments","")
A71: 10 | B71: Implement Operational controls securely | C71: 1 | D71: Are the operational controls implemented securely? | E71: Yes | G71: =IF(F71="Yes"," Operational controls are implemented securely.",IF(OR(F71="No",F71="NA"),"Recommended to Implement Operational controls securely.","")) | H71: Partially. Health checks, processing limits, role controls, and error handling exist | J71: =IF(F71="Yes","Y","N") -> N | K71: =IF(AND(OR(F71="No",F71="NA"),ISBLANK(H71)),"Please enter your comments","")
A72: 11 | B72: Implement alerts and warnings for anomalies & misbehavior | C72: 1 | D72: Are alerts and warnings implemented for anomalies & misbehaviour? | E72: Yes | G72: =IF(F72="Yes","Alerts and warnings are implemented for anomalies & misbehavior.",IF(OR(F72="No",F72="NA"),"Recommended to implement alerts and warnings for anomalies & misbehavior.","")) | H72: no | J72: =IF(F72="Yes","Y","N") -> N | K72: =IF(AND(OR(F72="No",F72="NA"),ISBLANK(H72)),"Please enter your comments","")
A73: 12 | B73: Generate unique transaction ids for sensitive transactions | C73: 1 | D73: Are unique transaction IDs generated for sensitive transactions? | E73: =IF(F34="Yes","Yes","No") -> No | G73: =IF(F73="Yes","Unique transaction Ids are generated for sensitive transactions",IF(OR(F73="No",F73="NA"),"Recommended to generate unique transaction ids for sensitive transactions","")) | H73: Unique UUID-based identifiers are generated for deals, sessions, audit entries, uploads, and narrative/review versions. | J73: =IF(E73="No","Y",IF(OR(OR(F34="No",F34="NA"),F73="Yes"),"Y","N")) -> Y | K73: =IF(AND(OR(F73="No",F73="NA"),ISBLANK(H73)),"Please enter your comments","")
A74: Verification and validation
A75: 1 | B75: Do not rely/trust on any inputs from user, service or API | C75: 1 | D75: Are the inputs from user, service or API used only after validating the input data? | E75: Yes | G75: =IF(F75="Yes","Recommended not trust any inputs from user, service or APIs.",IF(OR(F75="No",F75="NA"),"Inputs from user, services/API are verified before using them.","")) | H75: Input types, formats, lengths, roles, and URLs are validated | J75: =IF(F75="Yes","Y","N") -> N | K75: =IF(AND(OR(F75="No",F75="NA"),ISBLANK(H75)),"Please enter your comments","")
A76: 2 | B76: Use whitelisting over blacklisting | C76: 1 | D76: Is whitelisting pattern used while validating for malicious content instead of using blacklisting pattern? | E76: Yes | G76: =IF(F76="Yes","Whitelisting pattern is used while validating for malicious content instead of using blacklisting pattern.",IF(OR(F76="No",F76="NA"),"Recommended to use whitelisiting pattern over blacklisting while validating the malicious content.","")) | H76: Allow-lists are used for roles, URL schemes, source types, and some file extensions. | J76: =IF(F76="Yes","Y","N") -> N | K76: =IF(AND(OR(F76="No",F76="NA"),ISBLANK(H76)),"Please enter your comments","")
A77: 3 | B77: Always validate at server side | C77: 1 | D77: Is validation done at server side? | E77: Yes | G77: =IF(F77="Yes","Validations are done at server side.",IF(OR(F77="No",F77="NA"),"Recommended to validate data at the server side.","")) | H77: Backend schemas and validation logic enforce input rules independently of frontend checks. | J77: =IF(F77="Yes","Y","N") -> N | K77: =IF(AND(OR(F77="No",F77="NA"),ISBLANK(H77)),"Please enter your comments","")
A78: 4 | B78: Validate source, context, syntax & semantics of data | C78: 1 | D78: Is the source, context, syntax & semantics of data validated? | E78: Yes | G78: =IF(F78="Yes","The source, context, syntax & semantics of data is validated.",IF(OR(F78="No",F78="NA"),"Recommended to validate the source, context, syntax & semantics of data.","")) | H78: Format and business-rule checks exist | J78: =IF(F78="Yes","Y","N") -> N | K78: =IF(AND(OR(F78="No",F78="NA"),ISBLANK(H78)),"Please enter your comments","")
A79: 5 | B79: Check length, type, magic number, size for the files | C79: 1 | D79: Are file being processed by the application? | E79: =IF(D79<>"NA","Yes","No") -> Yes | G79: =IF(OR(F79="No",F79="NA"),"No file are being processed by the application.","") | H79: Yes, files are processed | J79: =IF(F79="Yes",J80,IF(NOT(ISBLANK(F79)),"Y","N")) -> N
C80: 1.1 | D80: Is the file type, length, magic number & size checked for the file? | E80: =IF(F79="Yes","Yes","No") -> No | G80: =IF(F80="Yes","The file type, length, magic number & size are checked for the file.",IF(OR(F80="No",F80="NA"),"Recommended to check the file type, leagth, magic number & size for the file.","")) | J80: =IF(F80="Yes","Y","N") -> N | K80: =IF(AND(OR(F80="No",F80="NA"),ISBLANK(H80)),"Please enter your comments","")
A81: 6 | B81: Implement Centralized Validation Methods | C81: 1 | D81: Are there any centralized methods implemented for validation? | E81: Yes | G81: =IF(F81="Yes","Centralized methods are implemented for validation.",IF(OR(F81="No",F81="NA"),"Recommended to implement centralized methods for validation.","")) | H81: Partially. Reusable Pydantic schemas and shared validation functions are used | J81: =IF(F81="Yes","Y","N") -> N | K81: =IF(AND(OR(F81="No",F81="NA"),ISBLANK(H81)),"Please enter your comments","")
A82: 7 | B82: Use standard APIs like ESAPI, AntiSamy etc | C82: 1 | D82: Are standard APIs like ESAPI or Antisamy or apache commons validator used for verification and validation? | E82: =IF(F83="Yes","No","Yes") -> Yes | G82: =IF(F82="Yes","The application uses standard APIs for verification.",IF(OR(F82="No",F82="NA"),"Recommended to use standard APIs for verification.","")) | H82: Yes. The application uses FastAPI and Pydantic for validation | J82: =IF(F82="Yes","Y","N") -> N | K82: =IF(AND(OR(F82="No",F82="NA"),ISBLANK(H82)),"Please enter your comments","")
C83: 2 | D83: Others | E83: =IF(F82="Yes","No","Yes") -> Yes | K83: =IF(AND(F83="Yes",ISBLANK(H83)),"Please enter your comments","")
A84: 6 | B84: Check time of validation vs. time of usage | C84: 1 | D84: Whiile updating the data, does the application always validates the data or locks the data? | E84: Yes | G84: =IF(F84="Yes","Validation is done or data locking is performed at the time of usage.",IF(OR(F84="No",F84="NA"),"Recommended to validate the data or appropriate locking is done at the time of usage.","")) | H84: Update requests undergo server-side validation | J84: =IF(F84="Yes","Y","N") -> N | K84: =IF(AND(OR(F84="No",F84="NA"),ISBLANK(#REF!)),"Please enter your comments","")
A85: Session Management
A86: 1 | B86: Establish an appropriate session timeout period | C86: 1 | D86: Does the application has session timeout configured? | E86: =IF(F4="Yes","No","Yes") -> Yes | H86: Yes. Authenticated sessions expire after 12 hours | J86: =IF(F4="Yes","Y",J87) -> N | K86: =IF(AND(OR(F86="No",F86="NA"),ISBLANK(H84)),"Please enter your comments","")
C87: 1.1 | D87: Is it ensured to have session timeout configured for max 30 mins? | E87: =IF(F86="Yes","Yes","No") -> No | G87: =IF(OR(F87="No",F87="NA"),"Application has configurable timeout. However recommend to invalidate the session on 30mins idle time at server side.","") | H87: no | J87: =IF(F87="Yes",J88,"N") -> N | K87: =IF(AND(OR(F87="No",F87="NA"),ISBLANK(H87)),"Please enter your comments","")
C88: 1.1.1 | D88: Is the session invalidated on time out? | E88: =IF(AND(F86="Yes",F87="Yes"),"Yes","No") -> No | G88: =IF(F88="Yes","Application has configurable session timeout with max of 30mins. Session is invalidated on time-out at server side.",IF(OR(F88="No",F88="NA"),"Application has configurable timeout with max of 30mins. However recommend to invalidate the session on timeout at server side.","")) | H88: Implemented. Expired sessions are rejected and removed from the database when subsequently presented to the application. | J88: =IF(F88="Yes","Y","N") -> N | K88: =IF(AND(OR(F88="No",F88="NA"),ISBLANK(H88)),"Please enter your comments","")
A89: 2 | B89: After logout do not reuse the same SID for same or other user | C89: 1 | D89: Are the session IDs deleted after logout? | E89: =IF(F4="Yes","No","Yes") -> Yes | G89: =IF(F89="Yes","Same SIDs are not reused after logout.",IF(OR(F89="No",F89="NA"),"Recommended not to reuse the same SID for same or other user after logout.","")) | H89: Yes. The active server-side session is deleted and the browser cookie is cleared. | J89: =IF(F4="Yes","Y",IF(F89="Yes","Y","N")) -> N | K89: =IF(AND(OR(F89="No",F89="NA"),ISBLANK(H89)),"Please enter your comments","")
A90: 3 | B90: Session Identifiers must not be stored in query strings or hidden parameters | C90: 1 | D90: Are session identifiers stored in query strings or hidden parameters? | E90: =IF(F4="Yes","No","Yes") -> Yes | G90: =IF(F90="Yes","Session Identifiers must not be stored in query strings or hidden parameters.",IF(OR(F90="No",F90="NA"),"Session Identifiers are not stored in query strings or hidden parameters.","")) | H90: Yes. Session identifiers are stored only in cookies, not in query strings or hidden parameters. | J90: =IF(F4="Yes","Y",IF(F90="Yes","N",IF(NOT(ISBLANK(F90)),"Y","N"))) -> N | K90: =IF(AND(F90="Yes",ISBLANK(H90)),"Please enter your comments","")
A91: 4 | B91: Session IDs must not be stored in clear text at server | C91: 1 | D91: Are session identifiers or tokens stored securely at server. | E91: =IF(F4="Yes","No","Yes") -> Yes | G91: =IF(OR(F91="No","NA"),"Recommend to store the session identifiers or tokens securely at server side.","") -> #VALUE! | H91: Yes. Only a SHA-256 hash of the session token is stored in the database; the raw token is not stored server-side. | J91: =IF(F4="Yes","Y",IF(F91<>"Yes","N",IF(COUNTIF(J92:J93,"Y")>0,"Y","N"))) -> N | K91: =IF(AND(OR(F91="No",F91="NA"),ISBLANK(H91)),"Please enter your comments","")
C92: 1.1 | D92: Are session identifiers or tokens stored in persistent storage? | E92: =IF(OR(COUNTIF(F93:F94,"Yes")>0,F91<>"Yes"),"No","Yes") -> No | G92: =IF(F92="Yes","",IF(NOT(ISBLANK(F92)),"Session Ids are not stored in persistent storage.","")) | H92: Implemented. Session tokens are persisted only as SHA-256 hashes in the auth_sessions database table; raw tokens are not stored server-side. | J92: =IF(F92="Yes",J95,IF(NOT(ISBLANK(F92)),"Y","N")) -> N
C93: 1.2 | D93: Are session identifiers or tokens stored in server in-memory? | E93: =IF(OR(OR(F92="Yes",COUNTIF(F94,"Yes")>0),F91<>"Yes"),"No","Yes") -> No | G93: =IF(F93="Yes","Session identifiers or tokens stored securely in server in-memory.","") | H93: no | J93: =IF(F93="Yes","Y","N") -> N
C94: 1.3 | D94: Others | E94: =IF(OR(COUNTIF(F92:F93,"Yes")>0,F91<>"Yes"),"No","Yes") -> No | K94: =IF(AND(F94="Yes",ISBLANK(H94)),"Please enter your comments","")
C95: 1.1.1 | D95: Are session identifiers or tokens removed from the persistent storage on invalidation of the user session? | E95: =IF(AND(F91="Yes",F92="Yes"),"Yes","No") -> No | H95: Implemented. Session records are deleted on logout, when an expired token is presented, and during applicable password-change/reset invalidation. | J95: =IF(F95="Yes","Y","N") -> N | K95: =IF(AND(OR(F95="No",F95="NA"),ISBLANK(H95)),"Please enter your comments","")
A96: 5 | B96: Use framework's session manager for session ids | C96: 1 | D96: Are the session identifier (SID) generated with appropriate randomness and length using the framework's session manager rather than creating a weak SID using a home-grown algorithm? | E96: =IF(F4="Yes","No","Yes") -> Yes | G96: =IF(F96="Yes","Session IDs are generated with appropriate randomness and length using the framework's session manager ",IF(OR(F96="No",F96="NA"),"Recommended to use properly generated session IDs using framework's session manager.","")) | H96: Partially. The application uses a custom server-side session mechanism rather than FastAPI’s session manager, but tokens are securely generated using Python’s cryptographic secrets.token_urlsafe(48) function. | J96: =IF(E96="No","Y",IF(F96="Yes","Y","N")) -> N | K96: =IF(AND(OR(F96="No",F96="NA"),ISBLANK(H96)),"Please enter your comments","")
A97: 6 | B97: Configure different session timeouts for different roles or access areas | C97: 1 | D97: Are different session time out periods configured for different types of roles or access areas (e.g., Administrators would have shorter session time out period compared to other roles. Person accessing the application over internet would have shorter session time out period compared to person accessing the same application within Intranet)? | E97: =IF('Asset Info'!B10="No","No",IF(F86="Yes","Yes","No")) -> No | G97: =IF(F97="Yes","Different session timeouts are configured for different roles or access areas.",IF(OR(F97="No",F97="NA"),"Recommended to configure different session timeouts for different roles or access areas.","")) | H97: no | J97: =IF(E97="No","Y",IF('Asset Info'!B10="No","Y",IF(F97="Yes","Y","N"))) -> Y | K97: =IF(AND(OR(F97="No",F97="NA"),ISBLANK(H97)),"Please enter your comments","")
A98: 7 | B98: Renew the SID before a sensitive transaction | C98: 1 | D98: Are SIDs renewed before a sensitive transaction? | E98: =IF(F34="Yes","Yes","No") -> No | G98: =IF(F98="Yes","The application renews SIDs before sensitive transaction.",IF(OR(F98="No",F98="NA"),"Recommended to configure different session timeouts for different roles or access areas.","")) | H98: no | J98: =IF(E98="No","Y",IF(OR(OR(F34="No",F34="NA"),F98="Yes"),"Y","N")) -> Y | K98: =IF(AND(OR(F98="No",F98="NA"),ISBLANK(H98)),"Please enter your comments","")
A99: 8 | B99: Don't allow multiple session ids at the same time for the same account | C99: 1 | D99: Are multiple session IDs allowed for same account at the same time? | E99: =IF(F34="Yes","Yes","No") -> No | G99: =IF(F99="Yes","Recommended not have multiple session IDs for same account at the same time.",IF(OR(F99="No",F99="NA"),"Recommended to renew SIDs before any critical/sensitive transactions.","")) | H99: no | J99: =IF(E99="No","Y",IF(OR(F34="No",F34="NA"),"Y",IF(F99="Yes","N",IF(NOT(ISBLANK(F99)),"Y","N")))) -> Y | K99: =IF(AND(F99="Yes",ISBLANK(H99)),"Please enter your comments","")
A100: 9 | B100: Logout user forcefully after a sufficient active period | C100: 1 | D100: Is the user loggedout forcefully after sufficient active period? | E100: =IF(F34="Yes","Yes","No") -> No | G100: =IF(F100="Yes","User is logged out forcefully after certain active time.",IF(OR(F100="No",F100="NA"),"Recommended to logout user forcefully after a sufficient active period.","")) | H100: Implemented. Sessions have an absolute 12-hour expiry. Expired sessions are rejected and removed when subsequently used. | J100: =IF(E100="No","Y",IF(OR(OR(F34="No",F34="NA"),F100="Yes"),"Y","N")) -> Y | K100: =IF(AND(OR(F100="No",F100="NA"),ISBLANK(H100)),"Please enter your comments","")
...

Sheet Gen AI Audit Sheet
A1: TCS Confidential
A3: Application ID (As per ARM)
A4: Application Name
A5: Risk Category (Low / Medium / High / Very High)
A7: Sr.No | B7: Section | C7: Section Name | D7: Sub | E7: Requirement | F7: Application team Remarks | G7: Reviewer's Comments | H7: Benchmark ReferenceGuidelines
A8: 1 | B8: V1 | C8: Secure Configuration | D8: 1.1 | E8: Identify any components that store secrets, like API keys, for third-party systems, like hosted LLMs and vector databases, and ensure the secure handling of these credentials according to section V2.10 “Service Authentication” of the OWASP ASVS. | F8: The application uses Mistral API and PostgreSQL, currently supplied through environment variables (.env files are Git-ignored) | H8: 1.Have you utilized Azure Key Vault to store API keys and secret keys? 2.Have you ensured that a private connection is enabled?
A9: 2 | B9: V1 | C9: Secure Configuration | D9: 1.2 | E9: For self-hosted LLMs, ensure they are appropriately segregated within the network to prevent direct exposure to end-users unless such access is required. | F9: no | H9: Are Self Hosted LLM's utilized?
A10: 3 | B10: V1 | C10: Secure Configuration | D10: 1.3 | E10: Maintain an up-to-date inventory of all LLM instances and apply regular updates and patches to self-hosted models. | F10: no | H10: Are Self Hosted LLM's utilized?
A11: 4 | B11: V1 | C11: Secure Configuration | D11: 1.4 | E11: Perform and document regular configuration reviews for configuration settings associated with the LLM-powered system. | F11: Content filtering uses mistral-moderation-latest for custom instructions and output templates; flagged content is blocked and results are logged for review. Service endpoints for PostgreSQL, MCP are environment-configured, while CORS is currently limited to local development origins. A formal periodic configuration-review process and fail-closed moderation behavior must be established before production certification. | H11: How are these points being managed needs to be addressed 1. Content Filter Configuration 2. Endpoint Configuration
A12: 5 | B12: V2 | C12: Model Lifecycle | D12: 2.1 | E12: Ensure that the lifecycle of machine learning models is integrated into the existing Secure Software Development Lifecycle (SSDLC). Defined processes should exist and be available for each stage of the lifecycle of ML models. | F12: no | H12: Application team to confirm whether there is requirement to use new model/train model else this case will not be applicable
A13: 6 | B13: V2 | C13: Model Lifecycle | D13: 2.2 | E13: Document user stories defining the requirements and use cases for any new ML model being produced. | F13: no | H13: Application team will share the user story as per their usecase
A14: 7 | B14: V2 | C14: Model Lifecycle | D14: 2.3 | E14: Ensure that model training resources and datasets are acquired from trustworthy sources and validated for correctness or free from malicious data. | F14: Applicable to RAG data. Only authenticated deal owners can upload files, text, or URLs to deal-specific Mistral Document Libraries. Company data is owner-scoped, section URLs are validated, and retrieved source details and citations are recorded for verification. Duplicate legacy uploads are identified using SHA-256 hashes. | H14: Data used by UseCase/RAG (Retrival Augmented Generated / Grounded) needs to be verified [Applicable for Upload functionality in Gen AI UseCase]
A15: 8 | B15: V2 | C15: Model Lifecycle | D15: 2.4 | E15: Ensure that model training resources and datasets are properly secured from unauthorized modification once acquired. | F15: Uploaded RAG files are protected through session-based authentication, role-based access, and deal-level authorization. File metadata—including deal ID, filename, source type, size, Mistral file ID, and creation time—is stored, while uploads are recorded in application logs/traces. Files cannot be edited in place; changes require authorized deletion and re-upload. | H15: Have you confirmed whether there are mechanisms in place to monitor and log any access or modifications made to the training resources and datasets/ or whether activities related to files uploaded by users are being logged? This helps in detecting any unauthorized attempts to alter the data and provides a record for auditing purposes. Recommendation: Application has to maintain the authorization properly to avoid improper modification of data [Applicable for Upload functionality in Gen AI UseCase]
A16: 9 | B16: V2 | C16: Model Lifecycle | D16: 2.5 | E16: Ensure that the source of any training resources and datasets is documented. | F16: Applicable to RAG inputs. The application records company-library documents, deal-specific file/URL/text uploads, PostgreSQL source tables, and section URLs. Stored metadata includes source type, filename or URL, deal association, file/library ID, size, timestamp, and retrieved-source/citation details. | H16: For now, Application team has to maintain record of the datasets that is shared to LLM [Applicable for Upload functionality in Gen AI UseCase]
A17: 10 | B17: V2 | C17: Model Lifecycle | D17: 2.6 | E17: Ensure that any data cleaning or other modifications to the original training resources are tracked and auditable to reduce the risk of data poisoning from an insider threat. | F17: Uploaded files are treated only as RAG data and are not executed by the application. SHA-256 hashes, source metadata, extraction method, page count, and extracted content are recorded; OCR/upload operations are logged. User-provided instructions and templates are moderated, with flagged content blocked before generation. | H17: Application team to share information on below points 1. Application has to maintain checks to block harmful content from getting executed 2. Everything should get added in logs. [Applicable for Upload functionality in Gen AI UseCase]
A18: 11 | B18: V2 | C18: Model Lifecycle | D18: 2.7 | E18: Ensure that the intellectual property rights of model training resources and datasets are checked to avoid potential license or copyright infringement issues. Ensure this process is documented and auditable. | F18: no | H18: Application team to share information on below points 1. Data Ownership Mail 2. Plagarism Check (IRC) 3. All features in the AI Services should be first approved from Legal end.
A19: 12 | B19: V2 | C19: Model Lifecycle | D19: 2.8 | E19: Ensure that model training resources are audited for sensitive data (such as PII, internal company data, etc.) and cleaned before training to mitigate sensitive data exposure in model responses. | F19: no | H19: Privacy Approval to be shared by application team (for data sent to LLM as part of RAG/Context) for sensitive information [Applicable for Upload functionality in Gen AI UseCase]
... A93: 83 | B93: C6 | C93: Custom: Data Protection & Sanitization | D93: 6.11 | E93: Validate Data Encryption during transit and at rest for all sensitive communications and stored data | F93: Mistral communication uses HTTPS, and passwords/session tokens are protected using hashing. | H93: Whether you have examined network traffic to confirm the use of TLS for data in transit and inspected storage mechanisms to ensure encryption is applied to sensitive data?

Sheet Report
A1: Asset Registration ID | B1: ='Asset Info'!B1 -> Tipar-ID
A2: Tool Evaluation Status | B2: =IF('Asset Info'!B11="No",IF(COUNTIF(C11:C137,"Not Approved")>0,"Not Cleared","Cleared"),"Not Cleared") -> Not Cleared
A3: Reviewer Evaluation Status
A4: Reviewer Final Comments
A6: Total Applicable Checklist Items | B6: =SUM(B7:B8) -> 127
A7: Total Autoapproved | B7: =COUNTIF(C11:C137,"Approved") -> 14
A8: Total Not Autoapproved | B8: =COUNTIF(C11:C137,"Not Approved") -> 113
A10: Security Foundation Parameter | B10: Checklist category | C10: Approval Status
A11: Authentication and Password Management | B11: Strong password policy | C11: =IF(COUNTIF(Checklist!J3:Checklist!J5,"Y")>0,"Approved","Not Approved") -> Not Approved
B12: Secure storage of credentials / keys | C12: =IF(Checklist!J9="Y","Approved","Not Approved") -> Not Approved
B13: Unique Id for each user | C13: =IF(Checklist!J11="Y","Approved","Not Approved") -> Not Approved
B14: Unique token for new session | C14: =IF(Checklist!J13="Y","Approved","Not Approved") -> Not Approved
B15: Logout | C15: =IF(Checklist!J15="Y","Approved","Not Approved") -> Not Approved
B16: Password management event logging | C16: =IF(Checklist!J18="Y","Approved","Not Approved") -> Not Approved
B17: Encrypted communication for secrets in transit | C17: =IF(Checklist!J20="Y","Approved","Not Approved") -> Not Approved
B18: Secure password recovery | C18: =IF(COUNTIF(Checklist!J22:Checklist!J27,"Y")>0,"Approved","Not Approved") -> Not Approved
B19: Latest version of TLS used for communication | C19: =IF(Checklist!J28="Y","Approved","Not Approved") -> Not Approved
B20: Anti-automation controls | C20: =IF(Checklist!J30="Y","Approved","Not Approved") -> Not Approved
B21: Multi-factor authentication for sensitive transactions | C21: =IF(Checklist!J34="Y","Approved","Not Approved") -> Not Approved
B22: IP based restriction for critical functionality | C22: =IF(Checklist!J37="Y","Approved","Not Approved") -> Not Approved
A23: Audit-trails and Logging | B23: Clock synchronization for all devices and servers | C23: =IF(Checklist!J40="Y","Approved","Not Approved") -> Not Approved
B24: Capture at least source IP address, timestamp, action owner Id, event Id and resource Id | C24: =IF(Checklist!J41="Y","Approved","Not Approved") -> Not Approved
B25: Differentiate events from errors | C25: =IF(Checklist!J42="Y","Approved","Not Approved") -> Not Approved
B26: Append only mode for trails and logs | C26: =IF(Checklist!J43="Y","Approved","Not Approved") -> Not Approved
B27: Use the standard APIs or libraries for logging (such as Log4j, Log4Net) | C27: =IF(Checklist!J44="Y","Approved","Not Approved") -> Not Approved
B28: Maintain audit-trail for administrative actions separately | C28: =IF(Checklist!J46="Y","Approved","Not Approved") -> Not Approved
B29: Log sensitive information in encrypted format. | C29: =IF(Checklist!J47="Y","Approved","Not Approved") -> Not Approved
B30: Plan sufficient disk space for logs. | C30: =IF(Checklist!J49="Y","Approved","Not Approved") -> Not Approved
B31: Appropriately select logging strategy based on date, user or events. | C31: =IF(COUNTIF(Checklist!J50:Checklist!J52,"Y")>0,"Approved","Not Approved") -> Not Approved
B32: Periodically analyze logs for anomaly or misbehavior | C32: =IF(Checklist!J54="Y","Approved","Not Approved") -> Not Approved
B33: Have restricted access for logs. | C33: =IF(Checklist!J56="Y","Approved","Not Approved") -> Not Approved
B34: Encrypt admin audit-trail and protect it from admin. | C34: =IF(Checklist!J57="Y","Approved","Not Approved") -> Not Approved
A35: Access Control | B35: Validate each request for authorization | C35: =IF(Checklist!J59="Y","Approved","Not Approved") -> Not Approved
B36: Always rely on Server Side data for access control decisions | C36: =IF(Checklist!J60="Y","Approved","Not Approved") -> Not Approved
B37: Offer minimal functionality to anonymous users | C37: =IF(Checklist!J61="Y","Approved","Not Approved") -> Not Approved
B38: Create centralized access control system through ACL | C38: =IF(Checklist!J63="Y","Approved","Not Approved") -> Not Approved
B39: Provide no privileges to an account when it is first created | C39: =IF(Checklist!J65="Y","Approved","Not Approved") -> Not Approved
B40: Classify data to perform Encryption, Hashing, Encoding or Masking | C40: =IF(Checklist!J66="Y","Approved","Not Approved") -> Not Approved
B41: Restrict a normal user's access to system resources | C41: =IF(Checklist!J67="Y","Approved","Not Approved") -> Not Approved
B42: Maintain Audit Trails for sensitive Transactions | C42: =IF(Checklist!J68="Y","Approved","Not Approved") -> Approved
B43: Generate sensitive content on the fly | C43: =IF(Checklist!J69="Y","Approved","Not Approved") -> Not Approved
B44: Implement Operational controls securely | C44: =IF(Checklist!J71="Y","Approved","Not Approved") -> Not Approved
B45: Implement alerts and warnings for anomalies & misbehavior | C45: =IF(Checklist!J72="Y","Approved","Not Approved") -> Not Approved
B46: Generate unique transaction ids for sensitive transactions | C46: =IF(Checklist!J73="Y","Approved","Not Approved") -> Approved
A47: Verification & Validation | B47: Do not rely/trust on any inputs from user, service or API | C47: =IF(Checklist!J75="Y","Approved","Not Approved") -> Not Approved
B48: Use whitelisting over blacklisting | C48: =IF(Checklist!J76="Y","Approved","Not Approved") -> Not Approved
B49: Always validate at server side | C49: =IF(Checklist!J77="Y","Approved","Not Approved") -> Not Approved
B50: Validate source, context, syntax & semantics of data | C50: =IF(Checklist!J78="Y","Approved","Not Approved") -> Not Approved
B51: Check length, type, magic number, size for the files | C51: =IF(Checklist!J79="Y","Approved","Not Approved") -> Not Approved
B52: Implement Centralized Validation Methods | C52: =IF(Checklist!J81="Y","Approved","Not Approved") -> Not Approved
B53: Use standard APIs like ESAPI, AntiSamy etc | C53: =IF(Checklist!J82="Y","Approved","Not Approved") -> Not Approved
B54: Check time of validation vs. time of usage | C54: =IF(Checklist!J84="Y","Approved","Not Approved") -> Not Approved
A55: Session Management | B55: Establish an appropriate session timeout period | C55: =IF(Checklist!J86="Y","Approved","Not Approved") -> Not Approved
B56: After logout do not reuse the same SID for same or other user | C56: =IF(Checklist!J89="Y","Approved","Not Approved") -> Not Approved
B57: Session Identifiers must not be stored in query strings or hidden parameters | C57: =IF(Checklist!J90="Y","Approved","Not Approved") -> Not Approved
B58: Session IDs must not be stored in clear text at server | C58: =IF(Checklist!J91="Y","Approved","Not Approved") -> Not Approved
B59: Use framework's session manager for session ids | C59: =IF(Checklist!J96="Y","Approved","Not Approved") -> Not Approved
B60: Configure different session timeouts for different roles or access areas | C60: =IF(Checklist!J97="Y","Approved","Not Approved") -> Approved
B61: Renew the SID before a sensitive transaction | C61: =IF(Checklist!J98="Y","Approved","Not Approved") -> Approved
B62: Don't allow multiple session ids at the same time for the same account | C62: =IF(Checklist!J99="Y","Approved","Not Approved") -> Approved
B63: Logout user forcefully after a sufficient active period | C63: =IF(Checklist!J100="Y","Approved","Not Approved") -> Approved
B64: Log all attempts made with invalid Session IDs | C64: =IF(Checklist!J101="Y","Approved","Not Approved") -> Not Approved
A65: Error & exception handling | B65: Resource specific exception | C65: =IF(Checklist!J103="Y","Approved","Not Approved") -> Not Approved
B66: No empty try / catch / finally blocks | C66: =IF(Checklist!J104="Y","Approved","Not Approved") -> Not Approved
B67: Return value check | C67: =IF(Checklist!J105="Y","Approved","Not Approved") -> Not Approved
B68: Display need to know information | C68: =IF(Checklist!J106="Y","Approved","Not Approved") -> Not Approved
B69: Error messages sanitation | C69: =IF(Checklist!J107="Y","Approved","Not Approved") -> Not Approved
B70: Failures do not expose internal information | C70: =IF(Checklist!J108="Y","Approved","Not Approved") -> Not Approved
B71: Use error code book | C71: =IF(Checklist!J109="Y","Approved","Not Approved") -> Not Approved
B72: Centrally managing error and exceptions | C72: =IF(Checklist!J110="Y","Approved","Not Approved") -> Not Approved
B73: Rollback to secure state during crash or function failure | C73: =IF(Checklist!J111="Y","Approved","Not Approved") -> Not Approved
B74: Alarm when exception in critical transaction | C74: =IF(Checklist!J112="Y","Approved","Not Approved") -> Approved
A75: Data Security & Privacy | B75: Collect end user data only if absolutely necessary and relevant | C75: =IF(COUNTIF(Checklist!J114:Checklist!J116,"Y")>0,"Approved","Not Approved") -> Not Approved
B76: Take users consent for data collection, retention, process, storage & sharing | C76: =IF(Checklist!J117="Y","Approved","Not Approved") -> Approved
B77: All requests containing data must use POST Method | C77: =IF(Checklist!J118="Y","Approved","Not Approved") -> Not Approved
B78: Disable client side caching for sensitive information | C78: =IF(Checklist!J119="Y","Approved","Not Approved") -> Not Approved
B79: Perform periodic VA & PT of the systems, network and application | C79: =IF(Checklist!J120="Y","Approved","Not Approved") -> Not Approved
B80: Securely export data in reports, print records, receipts, invoices, etc. | C80: =IF(Checklist!J121="Y","Approved","Not Approved") -> Not Approved
B81: Choose strong encryption, masking or tokenisation | C81: =IF(Checklist!J122="Y","Approved","Not Approved") -> Not Approved
B82: Ensure right level of data access in creating, reading, altering or deleting | C82: =IF(Checklist!J123="Y","Approved","Not Approved") -> Not Approved
B83: Use OS specific mechanism for key management | C83: =IF(Checklist!J124="Y","Approved","Not Approved") -> Not Approved
A84: Transport Layer Protection | B84: Use Strong Keys & Protect Them | C84: =IF(Checklist!J126="Y","Approved","Not Approved") -> Not Approved
B85: Use Fully Qualified Names in Certificates | C85: =IF(Checklist!J127="Y","Approved","Not Approved") -> Not Approved
B86: Use "Secure" Cookie Flag | C86: =IF(COUNTIF(Checklist!J128:Checklist!J129,"Y"),"Approved","Not Approved") -> Not Approved
B87: Keep Sensitive Data Out of the URL | C87: =IF(Checklist!J130="Y","Approved","Not Approved") -> Not Approved
B88: Use a Certificate supporting required Domain Names | C88: =IF(Checklist!J131="Y","Approved","Not Approved") -> Not Approved
B89: Do Not Use Wildcard Certificates | C89: =IF(Checklist!J132="Y","Approved","Not Approved") -> Not Approved
B90: Do Not Provide Non-TLS Pages for Secure Content | C90: =IF(COUNTIF(Checklist!J133:Checklist!J134,"Y")>0,"Approved","Not Approved") -> Not Approved
B91: Use an Appropriate Certification Authority | C91: =IF(Checklist!J135="Y","Approved","Not Approved") -> Not Approved
B92: Only Support Strong Protocols | C92: =IF(Checklist!J136="Y","Approved","Not Approved") -> Not Approved
B93: Use HTTP Strict Transport Security & Public Key Pinning | C93: =IF(Checklist!J137="Y","Approved","Not Approved") -> Not Approved
B94: Do Not Mix TLS and Non-TLS Content | C94: =IF(Checklist!J138="Y","Approved","Not Approved") -> Approved
A95: Business Logic Security | B95: Identify Business Rules separately | C95: =IF(Checklist!J140="Y","Approved","Not Approved") -> Not Approved
B96: Derive Test/Abuse Cases | C96: =IF(Checklist!J141="Y","Approved","Not Approved") -> Not Approved
B97: Do not allow any backdoor entries | C97: =IF(Checklist!J142="Y","Approved","Not Approved") -> Not Approved
B98: Perform Sanity Checks | C98: =IF(Checklist!J143="Y","Approved","Not Approved") -> Not Approved
B99: Do not make requests guessable | C99: =IF(Checklist!J144="Y","Approved","Not Approved") -> Not Approved
B100: Do not complicate implementation | C100: =IF(Checklist!J145="Y","Approved","Not Approved") -> Not Approved
B101: Check for required accuracy and completeness | C101: =IF(Checklist!J146="Y","Approved","Not Approved") -> Not Approved
B102: Track the assets or inventory on regular frequency | C102: =IF(Checklist!J147="Y","Approved","Not Approved") -> Not Approved
...
